CHANGELOG.txt
LICENCE.txt
MANIFEST.in
README.txt
setup.py
torchsdktest/__init__.py
torchsdktest/client.py
torchsdktest/errors.py
torchsdktest/initialiser.py
torchsdktest/torch_client.py
torchsdktest/torch_http_client.py
torchsdktest.egg-info/PKG-INFO
torchsdktest.egg-info/SOURCES.txt
torchsdktest.egg-info/dependency_links.txt
torchsdktest.egg-info/requires.txt
torchsdktest.egg-info/top_level.txt
torchsdktest/events/__init__.py
torchsdktest/events/generic_event.py
torchsdktest/events/job_events.py
torchsdktest/events/log_events.py
torchsdktest/events/span_event.py
torchsdktest/examples/__init__.py
torchsdktest/examples/example_1_pipeline.py
torchsdktest/examples/example_2_pipeline.py
torchsdktest/examples/example_3_1_pipeline.py
torchsdktest/examples/example_3_2_pipeline.py
torchsdktest/examples/example_datasource_workflow.py
torchsdktest/examples/example_datasource_workflow_2.py
torchsdktest/examples/pipeline_demo.py
torchsdktest/models/__init__.py
torchsdktest/models/asset.py
torchsdktest/models/assetType.py
torchsdktest/models/create_asset.py
torchsdktest/models/datasource.py
torchsdktest/models/job.py
torchsdktest/models/pipeline.py
torchsdktest/models/snapshot.py
torchsdktest/models/span.py
torchsdktest/models/span_context.py